shuguo/__init__.py
shuguo-0.2.dist-info/LICENCE.txt
shuguo-0.2.dist-info/METADATA
shuguo-0.2.dist-info/WHEEL
shuguo-0.2.dist-info/top_level.txt
shuguo-0.2.dist-info/RECORD
