Metadata-Version: 2.1
Name: shuguo
Version: 0.2
Summary: shuguo
Author: hushuguo
Author-email: hushuguo@outlook.com
License: MIT
License-File: LICENCE.txt
Requires-Dist: numpy (>=1.11.1)
